{
  "objectInfo" : {
    "id" : "0cxOm2p3uvwbj93msWl1kI",
    "name" : "Versioned_Folder3",
    "type" : "Folder",
    "metadata" : {
      "modelVersion" : {
        "major" : 0,
        "minor" : 0
      },
      "repoInfo" : null,
      "contextAttributes" : [ ],
      "additionalInfo" : {
        "description" : "",
        "contentType" : null,
        "documentState" : "COMPLETE"
      }
    }
  },
  "dataFileExtension" : "json",
  "updateTime" : "2023-08-21T05:02:09.880Z",
  "objectRefs" : [ ]
}